{
    "buyers": {"Tarvin": {
        "wishlisted": [{
            "Rental Price": "10",
            "Condition": "Good",
            "Title": "Adopt Algebra",
            "Author": "Author",
            "Is Rented": false,
            "Subject": "Math"
        }],
        "buyerName": "Tarvin"
    }},
    "bookMap": {"Math": [{
        "Rental Price": "10",
        "Condition": "Good",
        "Title": "Adopt Algebra",
        "Author": "Author",
        "Is Rented": false,
        "Subject": "Math"
    }]}
}